plant_disease_classification/__init__.py
plant_disease_classification/__main__.py
plant_disease_classification/api.py
plant_disease_classification/constant.py
plant_disease_classification/network.py
plant_disease_classification/plant_disease_classifier.py
plant_disease_classification-0.2.0.dist-info/COPYING
plant_disease_classification-0.2.0.dist-info/LICENSE
plant_disease_classification-0.2.0.dist-info/METADATA
plant_disease_classification-0.2.0.dist-info/NOTICE
plant_disease_classification-0.2.0.dist-info/WHEEL
plant_disease_classification-0.2.0.dist-info/top_level.txt
plant_disease_classification-0.2.0.dist-info/RECORD
