Metadata-Version: 2.1
Name: plant-disease-classification
Version: 0.2.0
Summary: A Python module that classifies disease on plants
Home-page: https://github.com/abdullahselek/plant-disease-classification
Author: Abdullah Selek
Author-email: abdullahselek@gmail.com
Maintainer: Abdullah Selek
Maintainer-email: abdullahselek@gmail.com
License: MIT License
Download-URL: https://pypi.org/project/plant-disease-classification/
Keywords: plant disease classification,neural networks,pytorch,convolutional neural networks,plants,disease
Platform: Any
Classifier: Intended Audience :: Developers
Classifier: License :: OSI Approved :: MIT License
Classifier: Operating System :: OS Independent
Classifier: Topic :: Software Development :: Libraries :: Python Modules
Classifier: Programming Language :: Python
Classifier: Programming Language :: Python :: 3
Classifier: Programming Language :: Python :: 3.5
Classifier: Programming Language :: Python :: 3.6
Classifier: Programming Language :: Python :: 3.7
Classifier: Programming Language :: Python :: 3.8
Classifier: Programming Language :: Python :: 3.9
Requires-Python: >=3.5
Requires-Dist: plant-disease-classification-models (==0.1.0)
Requires-Dist: torch (==1.7.1)
Requires-Dist: torchvision (==0.8.2)
Requires-Dist: numpy (==1.19.4)
Requires-Dist: Pillow (==8.0.1)
